{"version":1,"resource":"vscode-remote://wsl%2Bubuntu/home/denno/myPersonalWebsite/index.html","entries":[{"id":"Z7ws.html","timestamp":1660346868302},{"id":"MDBq.html","timestamp":1660386176424},{"id":"Gf8M.html","timestamp":1660386235334},{"id":"6Up0.html","timestamp":1660386404534},{"id":"p66g.html","timestamp":1660387145564},{"id":"b4AX.html","timestamp":1660387201144},{"id":"tbx2.html","timestamp":1660389463314},{"id":"jDwU.html","timestamp":1660390250544},{"id":"F9Or.html","timestamp":1660391560184},{"id":"ajOZ.html","timestamp":1660391973294},{"id":"gqVx.html","timestamp":1660392115874},{"id":"fbYO.html","timestamp":1660392409564},{"id":"ACfL.html","timestamp":1660392501374},{"id":"v1yZ.html","timestamp":1660393203714}]}